causalimpact_gibbs/__init__.py
causalimpact_gibbs/causalimpact_lib.py
causalimpact_gibbs/causalimpact_lib_test.py
causalimpact_gibbs/data.py
causalimpact_gibbs/data_test.py
causalimpact_gibbs/indices.py
causalimpact_gibbs/indices_test.py
causalimpact_gibbs/plot.py
causalimpact_gibbs/plot_test.py
causalimpact_gibbs/posterior_processing.py
causalimpact_gibbs/posterior_processing_test.py
causalimpact_gibbs/standardize.py
causalimpact_gibbs/standardize_test.py
causalimpact_gibbs/summary.py
causalimpact_gibbs/summary_test.py
causalimpact_gibbs/testdata/data.csv
causalimpact_gibbs/testdata/test_report_text_1.txt
causalimpact_gibbs/testdata/test_report_text_2.txt
causalimpact_gibbs/testdata/test_report_text_3.txt
causalimpact_gibbs/testdata/test_report_text_4.txt
causalimpact_gibbs/testdata/test_summary_output.txt
tfp_causalimpact_customized-0.2.20.dist-info/METADATA
tfp_causalimpact_customized-0.2.20.dist-info/WHEEL
tfp_causalimpact_customized-0.2.20.dist-info/licenses/LICENSE
tfp_causalimpact_customized-0.2.20.dist-info/RECORD
