Metadata-Version: 2.4
Name: tfp_causalimpact_customized
Version: 0.2.20
Summary: A stable version of the tfcasualimpact package
License-File: LICENSE
Requires-Python: >=3.10
Requires-Dist: altair>=5.5.0
Requires-Dist: arviz>=0.20.0
Requires-Dist: japanize-matplotlib>=1.1.3
Requires-Dist: matplotlib>=3.9.3
Requires-Dist: numpy<=2.1.0
Requires-Dist: pandas>=2.2.3
Requires-Dist: plotly>=5.24.1
Requires-Dist: tensorflow-probability>=0.25.0
Requires-Dist: tensorflow>=2.18.0
Requires-Dist: tf-keras>=2.18.0
